{
  "appPageId" : "77c302db-2adc-4665-a391-b8cfe22bfeed",
  "componentName" : "siteforce:sldsOneColLayout",
  "dataProviders" : [ ],
  "id" : "ce41966f-3342-4959-abba-054daa66325b",
  "label" : "Topic Catalog",
  "regions" : [ {
    "components" : [ {
      "componentAttributes" : {
        "bannerText" : "",
        "bannerTextWithKnowledge" : "Explore other <a href=\"javascript:void(0)\" class=\"headlineArticles\">articles</a> and <a href=\"javascript:void(0)\" class=\"headlineDiscussions\">discussions</a> on this topic.",
        "bannerTextWithoutKnowledge" : "Explore other <a href=\"javascript:void(0)\" class=\"headlineDiscussions\">discussions</a> on this topic.",
        "pageType" : "",
        "showSubTopics" : true,
        "title" : "Topics",
        "uniqueNameOrId" : ""
      },
      "componentName" : "forceCommunity:headline",
      "id" : "ca7d62c8-0c4a-4cd0-8a7c-7ef752dadcf2",
      "renderPriority" : "NEUTRAL",
      "renditionMap" : { },
      "type" : "component"
    } ],
    "id" : "ceb8167f-7223-4a84-9958-595ccad05672",
    "regionName" : "header",
    "type" : "region"
  }, {
    "components" : [ {
      "componentAttributes" : { },
      "componentName" : "forceCommunity:topicCatalog",
      "id" : "42703852-3c94-4606-8dcf-7151460871a3",
      "renderPriority" : "NEUTRAL",
      "renditionMap" : { },
      "type" : "component"
    } ],
    "id" : "fc83ac31-4db6-452a-a3a8-88d5cc80ceac",
    "regionName" : "content",
    "type" : "region"
  }, {
    "id" : "a79ab32f-5580-4be5-bef2-c7b9ffd222a6",
    "regionName" : "footer",
    "type" : "region"
  }, {
    "components" : [ {
      "componentAttributes" : {
        "customHeadTags" : "",
        "description" : "",
        "title" : "Topic Catalog"
      },
      "componentName" : "forceCommunity:seoAssistant",
      "id" : "e18c6bee-148d-42e5-b191-8e4b87feabfb",
      "renditionMap" : { },
      "type" : "component"
    } ],
    "id" : "d5101b06-1539-4f28-9c2f-21c1244ae827",
    "regionName" : "sfdcHiddenRegion",
    "type" : "region"
  } ],
  "themeLayoutType" : "Inner",
  "type" : "view",
  "viewType" : "topic-catalog"
}